[
  {
    "city_mpg": 24,
    "class": "subcompact car",
    "combination_mpg": 27,
    "cylinders": 4,
    "displacement": 2,
    "drive": "rwd",
    "fuel_type": "gas",
    "highway_mpg": 32,
    "make": "bmw",
    "model": "230i coupe",
    "transmission": "a",
    "year": 2020,
    "name": "bmw 230i coupe 2020",
    "img": "/Img/230i.jpg",
    "price": 26000,
    "body_type": "Coupe"
  },
  {
    "city_mpg": 24,
    "class": "subcompact car",
    "combination_mpg": 27,
    "cylinders": 4,
    "displacement": 2,
    "drive": "rwd",
    "fuel_type": "gas",
    "highway_mpg": 34,
    "make": "bmw",
    "model": "430i convertible",
    "transmission": "a",
    "year": 2019,
    "name": "bmw 430i convertible 2019",
    "img": "/Img/430i.jpg",
    "price": 32000,
    "body_type": "Cabrio"
  },
  {
    "city_mpg": 19,
    "class": "large car",
    "combination_mpg": 22,
    "cylinders": 6,
    "displacement": 3,
    "drive": "awd",
    "fuel_type": "gas",
    "highway_mpg": 28,
    "make": "bmw",
    "model": "740i xdrive",
    "transmission": "a",
    "year": 2017,
    "name": "bmw 740i xdrive 2017",
    "img": "/Img/740i.jpg",
    "price": 30000,
    "body_type": "Limousine"
  },
  {
    "city_mpg": 22,
    "class": "two seater",
    "combination_mpg": 26,
    "cylinders": 4,
    "displacement": 2,
    "drive": "rwd",
    "fuel_type": "gas",
    "highway_mpg": 32,
    "make": "bmw",
    "model": "z4 sdrive28i",
    "transmission": "a",
    "year": 2016,
    "name": "bmw z4 sdrive28i 2016",
    "img": "/Img/z4.jpg",
    "price": 22000,
    "body_type": "Coupe"
  },
  {
    "city_mpg": 13,
    "class": "two seater",
    "combination_mpg": 16,
    "cylinders": 10,
    "displacement": 5.2,
    "drive": "awd",
    "fuel_type": "gas",
    "highway_mpg": 20,
    "make": "audi",
    "model": "r8 awd",
    "transmission": "a",
    "year": 2020,
    "name": "audi r8 awd 2020",
    "img": "/Img/r8.jpg",
    "price": 90000,
    "body_type": "Coupe"
  },
  {
    "city_mpg": 19,
    "class": "standard sport utility vehicle",
    "combination_mpg": 21,
    "cylinders": 6,
    "displacement": 3,
    "drive": "awd",
    "fuel_type": "gas",
    "highway_mpg": 25,
    "make": "audi",
    "model": "q7",
    "transmission": "a",
    "year": 2019,
    "name": "audi q7 2019",
    "img": "/Img/q7.jpg",
    "price": 38000,
    "body_type": "SUV"
  },
  {
    "city_mpg": 24,
    "class": "subcompact car",
    "combination_mpg": 27,
    "cylinders": 4,
    "displacement": 2,
    "drive": "awd",
    "fuel_type": "gas",
    "highway_mpg": 34,
    "make": "audi",
    "model": "a5 cabriolet quattro",
    "transmission": "a",
    "year": 2018,
    "name": "audi a5 cabriolet quattro 2018",
    "img": "/Img/a5.jpg",
    "price": 28000,
    "body_type": "Cabrio"
  },
  {
    "city_mpg": 20,
    "class": "midsize car",
    "combination_mpg": 24,
    "cylinders": 6,
    "displacement": 3,
    "drive": "awd",
    "fuel_type": "gas",
    "highway_mpg": 29,
    "make": "audi",
    "model": "a7 quattro",
    "transmission": "a",
    "year": 2016,
    "name": "audi a7 quattro 2016",
    "img": "/Img/a7.jpg",
    "price": 25000,
    "body_type": "Limousine"
  },
  {
    "city_mpg": 22,
    "class": "two seater",
    "combination_mpg": 26,
    "cylinders": 4,
    "displacement": 2,
    "drive": "awd",
    "fuel_type": "gas",
    "highway_mpg": 31,
    "make": "audi",
    "model": "tt roadster quattro",
    "transmission": "a",
    "year": 2015,
    "name": "audi tt roadster quattro 2015",
    "img": "/Img/tt.jpg",
    "price": 24000,
    "body_type": "Cabrio"
  },
  {
    "city_mpg": 24,
    "class": "large car",
    "combination_mpg": 28,
    "cylinders": 6,
    "displacement": 3,
    "drive": "awd",
    "fuel_type": "diesel",
    "highway_mpg": 36,
    "make": "audi",
    "model": "a8 l",
    "transmission": "a",
    "year": 2014,
    "name": "audi a8 l 2014",
    "img": "/Img/a8.jpg",
    "price": 19000,
    "body_type": "Limousine"
  },
  {
    "city_mpg": 19,
    "class": "small sport utility vehicle",
    "combination_mpg": 22,
    "cylinders": 4,
    "displacement": 2,
    "drive": "4wd",
    "fuel_type": "gas",
    "highway_mpg": 26,
    "make": "mercedes-benz",
    "model": "gle350 4matic",
    "transmission": "a",
    "year": 2020,
    "name": "mercedes-benz gle350 4matic 2020",
    "img": "/Img/gle350.jpg",
    "price": 42000,
    "body_type": "SUV"
  },
  {
    "city_mpg": 24,
    "class": "compact car",
    "combination_mpg": 27,
    "cylinders": 4,
    "displacement": 2,
    "drive": "4wd",
    "fuel_type": "gas",
    "highway_mpg": 32,
    "make": "mercedes-benz",
    "model": "cla250 4matic",
    "transmission": "a",
    "year": 2019,
    "name": "mercedes-benz cla250 4matic 2019",
    "img": "/Img/cla250.jpg",
    "price": 27000,
    "body_type": "Limousine"
  },
  {
    "city_mpg": 17,
    "class": "standard sport utility vehicle",
    "combination_mpg": 19,
    "cylinders": 6,
    "displacement": 3,
    "drive": "4wd",
    "fuel_type": "gas",
    "highway_mpg": 22,
    "make": "mercedes-benz",
    "model": "gls450 4matic",
    "transmission": "a",
    "year": 2017,
    "name": "mercedes-benz gls450 4matic 2017",
    "img": "/Img/gls450.jpg",
    "price": 35000,
    "body_type": "SUV"
  },
  {
    "city_mpg": 20,
    "class": "subcompact car",
    "combination_mpg": 23,
    "cylinders": 6,
    "displacement": 3,
    "drive": "rwd",
    "fuel_type": "gas",
    "highway_mpg": 29,
    "make": "mercedes-benz",
    "model": "e400 coupe",
    "transmission": "a",
    "year": 2016,
    "name": "mercedes-benz e400 coupe 2016",
    "img": "/Img/e400.jpg",
    "price": 26000,
    "body_type": "Coupe"
  },
  {
    "city_mpg": 13,
    "class": "two seater",
    "combination_mpg": 15,
    "cylinders": 8,
    "displacement": 6.2,
    "drive": "rwd",
    "fuel_type": "gas",
    "highway_mpg": 19,
    "make": "mercedes-benz",
    "model": "sls amg gt coupe",
    "transmission": "a",
    "year": 2015,
    "name": "mercedes-benz sls amg gt coupe 2015",
    "img": "/Img/sls.jpg",
    "price": 130000,
    "body_type": "Coupe"
  },
  {
    "city_mpg": 20,
    "class": "midsize car",
    "combination_mpg": 22,
    "cylinders": 6,
    "displacement": 3.5,
    "drive": "4wd",
    "fuel_type": "gas",
    "highway_mpg": 27,
    "make": "mercedes-benz",
    "model": "e350 4matic",
    "transmission": "a",
    "year": 2014,
    "name": "mercedes-benz e350 4matic 2014",
    "img": "/Img/e350.jpg",
    "price": 20000,
    "body_type": "Limousine"
  }
]
